samgeo/__init__.py
samgeo/caption.py
samgeo/common.py
samgeo/fast_sam.py
samgeo/fer.py
samgeo/hq_sam.py
samgeo/samgeo.py
samgeo/samgeo2.py
samgeo/samgeo3.py
samgeo/text_sam.py
samgeo/utmconv.py
segment_geospatial-1.1.0.dist-info/licenses/LICENSE
segment_geospatial-1.1.0.dist-info/METADATA
segment_geospatial-1.1.0.dist-info/WHEEL
segment_geospatial-1.1.0.dist-info/top_level.txt
segment_geospatial-1.1.0.dist-info/RECORD
