Metadata-Version: 2.4
Name: segment-geospatial
Version: 1.1.0
Summary: Meta AI' Segment Anything Model (SAM) for Geospatial Data.
Author-email: Qiusheng Wu <giswqs@gmail.com>
License: MIT license
Project-URL: Homepage, https://github.com/opengeos/segment-geospatial
Keywords: samgeo
Classifier: Development Status :: 2 - Pre-Alpha
Classifier: Intended Audience :: Developers
Classifier: License :: OSI Approved :: MIT License
Classifier: Natural Language :: English
Classifier: Programming Language :: Python :: 3
Classifier: Programming Language :: Python :: 3.10
Classifier: Programming Language :: Python :: 3.11
Classifier: Programming Language :: Python :: 3.12
Requires-Python: >=3.10
License-File: LICENSE
Requires-Dist: gdown
Requires-Dist: geopandas
Requires-Dist: huggingface_hub
Requires-Dist: matplotlib
Requires-Dist: numpy
Requires-Dist: opencv-python-headless
Requires-Dist: patool
Requires-Dist: Pillow
Requires-Dist: pyproj
Requires-Dist: rasterio
Requires-Dist: segment_anything
Requires-Dist: shapely
Requires-Dist: torch
Requires-Dist: torchvision
Requires-Dist: tqdm
Requires-Dist: xyzservices
Provides-Extra: core
Requires-Dist: gdown; extra == "core"
Requires-Dist: geopandas; extra == "core"
Requires-Dist: numpy; extra == "core"
Requires-Dist: opencv-python-headless; extra == "core"
Requires-Dist: patool; extra == "core"
Requires-Dist: Pillow; extra == "core"
Requires-Dist: pyproj>=3.7.2; extra == "core"
Requires-Dist: rasterio; extra == "core"
Requires-Dist: segment_anything; extra == "core"
Requires-Dist: shapely; extra == "core"
Requires-Dist: torch; extra == "core"
Requires-Dist: tqdm; extra == "core"
Provides-Extra: fast
Requires-Dist: segment_geospatial[core]; extra == "fast"
Requires-Dist: segment-anything-fast; extra == "fast"
Requires-Dist: sam2; extra == "fast"
Provides-Extra: fer
Requires-Dist: segment_geospatial[core]; extra == "fer"
Requires-Dist: gdal; extra == "fer"
Provides-Extra: hq
Requires-Dist: segment_geospatial[core]; extra == "hq"
Requires-Dist: segment_anything_hq; extra == "hq"
Requires-Dist: sam2; extra == "hq"
Requires-Dist: timm; extra == "hq"
Provides-Extra: samgeo
Requires-Dist: segment_geospatial[core]; extra == "samgeo"
Requires-Dist: huggingface_hub; extra == "samgeo"
Provides-Extra: samgeo2
Requires-Dist: segment_geospatial[samgeo]; extra == "samgeo2"
Requires-Dist: sam2; extra == "samgeo2"
Requires-Dist: xarray; extra == "samgeo2"
Requires-Dist: rioxarray; extra == "samgeo2"
Requires-Dist: scikit-image; extra == "samgeo2"
Requires-Dist: scipy; extra == "samgeo2"
Provides-Extra: samgeo3
Requires-Dist: segment_geospatial[core]; extra == "samgeo3"
Requires-Dist: sam3; extra == "samgeo3"
Requires-Dist: scikit-learn; extra == "samgeo3"
Requires-Dist: scikit-image; extra == "samgeo3"
Requires-Dist: transformers; extra == "samgeo3"
Requires-Dist: buildingregulariser; extra == "samgeo3"
Requires-Dist: leafmap; extra == "samgeo3"
Requires-Dist: localtileserver; extra == "samgeo3"
Requires-Dist: spacy; extra == "samgeo3"
Requires-Dist: triton>=3.5.1; sys_platform == "linux" and extra == "samgeo3"
Requires-Dist: triton-windows>=3.3.0.post19; sys_platform == "windows" and extra == "samgeo3"
Requires-Dist: transformers>=5.0.0rc0; extra == "samgeo3"
Requires-Dist: xarray; extra == "samgeo3"
Provides-Extra: text
Requires-Dist: segment_geospatial[samgeo2]; extra == "text"
Requires-Dist: groundingdino-py; extra == "text"
Provides-Extra: all
Requires-Dist: segment-geospatial[fast,fer,hq,samgeo,samgeo2,samgeo3,text]; extra == "all"
Provides-Extra: extra
Requires-Dist: leafmap; extra == "extra"
Requires-Dist: segment-geospatial[all]; extra == "extra"
Requires-Dist: localtileserver; extra == "extra"
Requires-Dist: ipykernel; extra == "extra"
Requires-Dist: fiona; extra == "extra"
Requires-Dist: matplotlib; extra == "extra"
Dynamic: license-file
